pyDeltaRCM/__init__.py
pyDeltaRCM/__main__.py
pyDeltaRCM/_version.py
pyDeltaRCM/debug_tools.py
pyDeltaRCM/default.yml
pyDeltaRCM/hook_tools.py
pyDeltaRCM/init_tools.py
pyDeltaRCM/iteration_tools.py
pyDeltaRCM/model.py
pyDeltaRCM/preprocessor.py
pyDeltaRCM/sed_tools.py
pyDeltaRCM/shared_tools.py
pyDeltaRCM/water_tools.py
pydeltarcm-2.1.9.dist-info/licenses/LICENSE
pydeltarcm-2.1.9.dist-info/METADATA
pydeltarcm-2.1.9.dist-info/WHEEL
pydeltarcm-2.1.9.dist-info/entry_points.txt
pydeltarcm-2.1.9.dist-info/top_level.txt
pydeltarcm-2.1.9.dist-info/RECORD
