Metadata-Version: 2.4
Name: pyDeltaRCM
Version: 2.1.9
Summary: Python version of original Matlab DeltaRCM.
Author-email: Andrew Moodie <amoodie@tamu.edu>
Maintainer-email: Andrew Moodie <amoodie@tamu.edu>
License: MIT
Project-URL: documentation, https://deltarcm.org/pyDeltaRCM
Project-URL: homepage, https://deltarcm.org/pyDeltaRCM
Project-URL: repository, https://github.com/DeltaRCM/pyDeltaRCM
Classifier: Intended Audience :: Science/Research
Classifier: License :: OSI Approved :: MIT License
Classifier: Operating System :: OS Independent
Classifier: Programming Language :: Python :: 3 :: Only
Classifier: Programming Language :: Python :: 3.11
Classifier: Programming Language :: Python :: 3.12
Classifier: Programming Language :: Python :: 3.13
Classifier: Topic :: Scientific/Engineering :: Hydrology
Classifier: Topic :: Scientific/Engineering :: Physics
Requires-Python: >=3.11
License-File: LICENSE
Requires-Dist: importlib-resources; python_version < "3.12"
Requires-Dist: matplotlib
Requires-Dist: scipy
Requires-Dist: netCDF4
Requires-Dist: pyyaml
Requires-Dist: numba
Requires-Dist: numpy
Provides-Extra: docs
Requires-Dist: sphinx; extra == "docs"
Provides-Extra: testing
Requires-Dist: coveralls; extra == "testing"
Requires-Dist: pytest; extra == "testing"
Requires-Dist: pytest-cov; extra == "testing"
Requires-Dist: pytest-mpl; extra == "testing"
Dynamic: license-file
